{
  "d840b70f-bf01-4b84-84ef-5c6a4b663d4e": {
    "id": "d840b70f-bf01-4b84-84ef-5c6a4b663d4e",
    "voiceId": "voice-1753042295",
    "voiceName": "ttt",
    "status": "completed",
    "progress": 95,
    "audioFiles": [
      "audio_000.wav"
    ],
    "language": "en",
    "epochs": 100,
    "speakerEmbedding": true,
    "type": "files",
    "created_at": 1753042298.3920314,
    "voice_characteristics": {
      "fundamental_freq": 153.7715606689453,
      "formant_shift": 1.5014086503112027,
      "spectral_centroid": 1501.4086503112028,
      "spectral_rolloff": 2952.7992039769347,
      "spectral_bandwidth": 1647.5112869618645,
      "tempo": 117.45383522727273,
      "zero_crossing_rate": 0.07171475900036858,
      "voice_energy": 0.018309175968170166,
      "voice_dynamics": 0.03584066778421402,
      "mfcc_mean": [
        -402.2196044921875,
        87.25970458984375,
        15.978327751159668,
        28.442947387695312,
        3.956267833709717,
        3.4923484325408936,
        3.4445555210113525,
        3.182039976119995,
        -1.6534404754638672,
        11.283825874328613,
        -3.505514144897461,
        0.16429585218429565,
        2.9532618522644043
      ],
      "vibrato_rate": 5.0,
      "voice_texture": 1.0466498473960588,
      "voice_warmth": 0.5352097016251376
    },
    "estimated_time_remaining": "0m 16s",
    "elapsed_time": "5m 22s",
    "transcriptions": [
      {
        "text": "A hallo alemaal, en elkom beide zoomer podcast. Ikka i vambag startet metven lijitisini. En lijitje van pomlin des enetis o plas. Ik heb zante min zakkenen, vinten min haarde hopte ik had, hangt goed tan alkaer ik moet ter gedur zetten, mij als is zerswar van. Ik had watergevangenende kom van mijn hand, ik pracht het naar zee, ik swam terug naar land tot stukje, woerstukje, deke slijn veranderd. Jij zij dat het klaar was, numde mije aadlass, sorry dat ik jano op handen draag. Jij doet of het niks was, kapt er veel maar vakt dat, galt je bent complex, maar nog hepe kraak. De zik weer kopt me spullen, bouheisen van karton. De preisie ik betaal om te denken dat het kon. Ik wist dat het zwaar was, niet dat het niet waar, was je wereld op mijn schouders, nooit andersom, nooit andersom. Jij had, een plok kan je wénje, wist niet dat ik er was, drog mij door de moder daarna, brog ik wat er op je porst, lag je stuin op plaats voor mij, ik wist dat het goed ging komen, toen was het moment voor mij. Jij zij dat het klaar was, numde mije aadlass, sorry dat ik jano op handen draag. Jij doet of het niks was, kapt er veel maar vakt dat, galt je bent complex, maar nog hepe kraak. De zik weer kopt me spullen, bouheisen van karton. De preisie ik betaal om te denken dat het kon. Ik wist dat het zwaar was, niet dat het niet waar, was je wereld op mijn schouders, nooit andersom, nooit andersom, niet waar, ik was weken reelebrand, kweeleweld, koseke, te veel gevraagd. Achter afbekeken waren het labieleweken, ik zat bij de binnenbreken, als jij het vraagt, maar jij zij dat het klaar was, numde mije aadlass, sorry dat ik jou nog op handen draag. Jij doet of het niks was, kapt er veel maar vakt dat, galt je bent complex, maar nog hepe kraak. De zik weer kopt me spullen, bouheisen van karton. De preisie ik betaal om te denken dat het kon. Ik wist dat het zwaar was, niet dat het niet waar, was je wereld op mijn schouders, nooit andersom, nooit andersom. Zodat, dat was het liedje van pomelintes adlass. Dat is ook de favorite zangeret van ons kleine limeloo. Ze vindt de superleuk om dat ze zelf haar gliedeje maakt, omdat ze zelf haar teksten maakt. Ik ga ook heel veel van poezie, en ik ga jullie ebidjes een gedicht voordragen van ton hermans en dat gedichte et de z. Ik wil alleen zijn met de z. Ik wil alleen zijn met het strand. Ik wil me ziel wat laten waren, niet me lijven me verstand. Ik wil gewoon een beetje dromen, rond de dingen die ik voel en de z. Ik weet het zeker dat ze weet wat ik betoel. Ik wil alleen zijn met de golven, ik wil alleen zijn met de lucht. Ik wil luister naar mijn abem, ik wil luister naar mijn z. Ik wil luister naar mijn zwijgen, daarna zal ik vergaan. En de z. Ik weet het zeker, zal mijn zwijgen wel verstaan. Ton hermans schrijft hele mooie gedichter, heel fijn, heel poeitis. En andere Nederlandse dichter die ik ook al heel fijn vind, en ik wil ook hele tofel boekersgericht is, en ik wil hem geen schmitt. En ik wil eens graag eeweljes boer, de regenworm en zijn moeder. Er was een regenworm in snake, die altijd naar de sterkeek en vluisterde, hoes schoon, hoes schoon. Zij moeder zei, oh, toet toch gewoon! Kijk naar beneden naar de grond, dat is normal, dat is gezond. Kijk naar beneden, zoals ik. En toen, toen kwam de leberk. Het wormpje dat naar boven staden, zag hem op tijd, een grob in daar. Maar moeder naar beneden kijk, werd opgegeten, daar in snake. Dus doe nooit wat je moeder zei. Dan komt het allemaal wel tijd. Heel, vrij vol, heel grappig ook allemaal. Ik wil wel nog rustisch eewetjes een liedje singen. Ik ga een liedje singen van een zangeres. En die zangeres heet eeva de roveren in bellische zangeres. Maar een heel groot repert waren. En ik ga een liedje singen en laat m'er je liedzin. Eewetjes een instrumentalstakje. En komt er zo meteen aam. Ik zit in over alle lei en over iedereen. Maar nooit is over mij. Maar al te vaak glijd op. Wij al zo verkopen. En hoe jij dat beschrijft. Bien idee je meer of krijg je het niet gezegd. Bij je fantasie maar dan levens echt. Laat m'er jou liedzin. Geef bij een zine jourenfriend. Ik wacht al zo lang. Wat nu geen tijd? Laat m'er liedzin. M'n stroven over een rijmaarik. Gelukkig zijn. Met een enkelhoort. Vrienden zeggen mij altijd. Je bent maar plogiat. Je maakt jezelf wat wij's. Maar ik geloven mij gevoel. En niet een goeie rant. Ik heb maar een doel. Krijg je me niet op papier. Ik help je graag op weg. Jeik ben je fantasie. Maar dan levens echt. Laat m'er jou liedzin. Geef bij een zine jourenfriend. Ik wacht al zo lang. Wat nu geen tijd? Laat m'er jou liedzin. Geef bij een zine jourenfriend. M'n stroven over een rijmaarik. Gelukkig zijn. Met een enkelhoort. En enkelhoort. Heb je geen idee je meer. K' help je graag op weg. Jeik ben je fantasie. Maar dan levens echt. Laat m'er jou liedzin. Geef bij een zine jourenfriend. Ik wacht al zo lang. Wat nu geen tijd? Laat m'er jou liedzin. Geef bij een zine jourenfriend. M'n stroven over een rijmaarik. Gelukkig zijn. Laat m'er jou liedzin. Geef bij een zine jourenfriend. Ik wacht al zo lang. Wat nu geen tijd? Laat m'er jou liedzin. Geef bij een zine jourenfriend. Gelukkig zijn. Met een en enkelhoort. Dat was het liedje van de roveren. We hadden een verder. K' eik kijkert eikertje nog. Ik dacht dat ik een heel leuk gedichtje wel is. Ik wilde het lieje. Bijvoorbeeld een kwot. Dat is ook wel heel fein. Een kwot is wel zo. Het land is warm, de weg is wet. Het duin is leeg, de zeen stil. De zon is grijs, de dag is heel. Dat was een heel speciaal kwot. Een keer die ik nu niet zelf zou kiezen. Ik heb het ook kwot, dus wel stoet schek. Denk iets mooi, zeg iets liefs. Dan heeft elke dag iets positiefs. En wist je dat een elskuuken, een ooit zelf, eerste en eil was? Elke wijze uel broed in een nest op een toekomst. Mama Eil leegd liefde vol in haar ei en toekomst. Mama Eil broed in een nest op een ei. En elke wijze uel was ooit zelf, eerste en eil skuuken. Mooi ha. Goed, twar overig, gaan we nog ebukjes praten. Ik ga misschien ebukjes een krante artikel te leren, maar vandaag zijn we zatterdag 12 juli. Als er een limme opkamp vertrokken met hero, die ze lene artikel twingen, vertrokken. Morgen vertrekts el jappen opkamp, hij vertrekte op hockeykamp, en haar bros gaat naar de hockeyclub draven. Hij had daar met sportways. Op hockeykamp worden aantal dagen. Wat gaan we ebukjes lezen? Ik zit hier op het nieuwsplatz. We gaan ebukjes zoeken, wat er interessant is om te lezen. Er staat ook altijd heel veel komkommer nieuws op. Het is ook om te komen op artit. Dus ik zoek wel iets leuk om te lezen, iets tak zelf ook graven lezen, iets tak nog niet weet. Er staan natuurlijk veel opkamp, maar we gaan ebukje opkamp, over Trump, en dat is een beetje tegen. Ik zie hier dat er vandaag. Een zoek-accit was aan de ze naar een keetje. Ik ga ebukje lezen. Zoek-accit met boten en helikopters naar vermist keentje bleikt valsallaren. Aan de kust van de banen zogtende hulpdiensten sind 16 ur naar een keentje van 5 jaar. Uiteindelijk bleek het om een valsallaren te gaan. Ratters speurde zij aan zij met boten uit water op ervlak af en ook brandweer Westhoek post oost deunkerke werd opgroepen. Ook de helikopter werd ingezet. Eindelijk bleek het om valsallaren te gaan. Een strandganger dacht dat zij een drinken in had gezien in ze en melde rattanderhiders, zeg in Helijn Engels, woordhoerster van polisizone Westpust. Er was de sprake van een keentje, maar dat kloppt niet. Er werd een groot schaalige zoek-accit opgestart, maar er werd niemand gevonden. Na ruim een ure is die zoek-accit dan ook stopgidets. Een duur grappie, denk ik dan, maar ik wil ookig is er niemand over te gaan. We gaan nog eens even just een liedje singen. Ik wil je dat in het niederland singen, dus ik ben even just aan het denken. Ik wil wel eens een liedje linge van Mira. Mira is een moderne kleinkunst. Zeg heeft niet zo heel veel nummers die bekend zijn, maar eetje daarvan die keerleuk. Zeg een grenzen. Grenzen van Mira. We gaan nog eens singen. Kan mijn grenzen niet? Ik kan mijn grenzen niet. Grenzen zijn voor mensen die. Nie weten waar naartoe. Ik ben toerisch tent leven noot lang hergesgebleven. Mijn idee over wat moet en wat mag verander van dag op dag. O, wat een feest. O, wat een feest. Ik kan mijn grenzen niet. Ik kan mijn grenzen niet. Grenzen zijn voor mensen die. Nie weten waar naartoe. Ik weet dat zo goed. Mijn vol duizend man. Mijn meenig meenig vrou. Dus wat neer jij zegt. O, schalt ik al van jou. Ik mij af van wie. Vraag ik mij af van wie. Ik kan mijn grenzen niet. Ik kan mijn grenzen niet. Grenzen zijn voor mensen die. Nie weten waar naartoe. Ik weet dat zo goed. Dan haven en hartzoek. Dan haven en hartzoek. Op een dag plak ik. Plak ik mijn grenzen af. Ik kan mijn grenzen niet. Ik kan mijn grenzen niet. Grenzen zijn voor mensen die. Nie weten waar naartoe. Ik kan mijn grenzen niet. Ik kan mijn grenzen niet. Grenzen zijn voor mensen die. Nie weten waar naartoe. En ik weet dat zo goed. En ik weet dat zo goed. Dat was et litje van mida. Als vervolger op etjes en een heel mooi kredichtje lesen. En het gedichtje gaat over mooie momenten. Soms zou ik de tijd willen vangen. Mijn mooiste momenten zorgvildig bewaardt. Met liefte, verzameld. Strikje eron. Al mijn fijne herinneringen dicht bij elkaar. En dat ik dan soms op een avond. Nog ebiedjes terug kan naartoe. Dat ik die mooiste momenten gewone naartoe dan kan. Zo maar nog eens opnie van. Wat fein is. Wat mooi was. Is nooit echt over of klaar. Als ik het heel vervolg met een strik eron bewaardt. Mooie. Ja, vind ik wel een mooie gedichtje. En het gedichtje over mooie momenten uit klopt ook wel een klein beetje. Als het wel onwisfein zijn om er toch nog eens eeudjes naartoe te mogen. Dus naar een mooi momenten. Of eens eeudjes terug in de tijd staan. Fein. Ho! Ben de kort gaan we ook op reis naar krowaasje. We gaan er heel veel dingetjes besoeken. We vertrekken in zeel uiteraart. Over de nachtreeren en dan rijden we naar Zell Amzee. Zell Amzee is een dorpje in Oostrijk. Een bekend dorpje. Het is een skigebied in de winter, maar dat er zeven zeer te kermeter biste is. Maar in de zomer is het ook wel een aanlokselijke plek. Het meerdataar lecht in Zell Amzee is uiteraart de Zellersie. En je kan er ook die hele mooie barge zien, bijvoorbeeld de kitssteinhoren, die 3.29 m hoog is. Dus gelegend in Kaproen, in Zellbach, in Oostrijk. Zwell is feinig, maar ik kijk er wel diewetjes naar uit, om diewetjes in de bergen te zijn, zoals vroegerige, vroegerige ik altijd op reis naar de bergen om te wandelen. Dat wandelen, dat moet nu niet persi voor mij, maar dat nog m'n keer uitzicht van de bergen en de rust uit de bergen pruin. Dat du die, dat is, ja dat wil ik wel hege recnochnikieren. Dus daarna reden we verder van Zellansie naar Lubliana. Lubliana is de hovstad van Slovenie. Na schet en hele schatige romantice hovstad. Wat kan je da allemaal tun? Lubliana is en van de kleinse hovstieden. Dus ze heeft niet zo'n hele lange leist met bezinsware, giden of highlights, maar wel super leuk. Dus dat's wel tof over a minis te de trip. Ies sprik datrou is eit als Lubliana, als het echt zo'jus moeten zengen Lubliana. Ik kan da heel goed met gewoent de voet door de stad. Ja, dat centrale plein, het prezeren squir, prezeren of squir is eit gekelemerk door een hele mooie rose, de rosekerk, die is niet te mist, en dat is echt wel een beetje de ontmoetingsplek voor de locals. En daar komen eigenlijk alles traten van Lubliana samen. Die ligt daar ook, die kerk aan een rivier, waar er drie bruggen overlopen. Die drie bruggen, en zei, ook al een touristische trekpleister. Wat je daar ook kan zien, is eit se castel van Lubliana, Lubliana is een ski grat, die ligt een beetje hoger, om 376 meter. Ja, dat er een heel mooi uitzicht. En ik kan maar de rode daken van Lubliana spotten. Je kak is en of je te voet erart toegraat, maar er is ook een lift. Als je te goed gaat, is 20 minutsje stappen en met het liftje, kosteert 6 euro heen en teruggevacht. Zo'n liftje is altijd wel leuk voor de kindjes. En ook voordem, maar wat is wat? Het zal wel warm zijn, dat in Lubliana. Wat kan je daar nog doen? Je hebt daar ook, de hele bekende drakenbrug. De draken is eigenlijk een beetje het symbol van Lubliana. Hij wakt eigenlijk over de stad en over de inwoners en zo'n gelieftemne in het castel. En zo'n zig daar ook wel te goed gedaan, hebben mandelijks aan een jonge vrouwe. En nu is dat hij, de stad hij heeft beschermd, is altijd ook ook wel eens de stad hebben aangevallen. Maar, als het draak over slagen was, dan is hij eigenlijk het symbol geworden van Lubliana van de stad. En dus, zeen standbeeld staat op de drakenbrug, de drakenbrug. En waar je toch ook nog niet kerk kan gaan keken. Niet zo ver van Lubliana, en je ook het prejudmakasteel, dat legt zo egen in de grootse maakt. Je hebt daar ook de grotte van bostonia, hele mooie grotte met de ruiwstied. Wat dat ook wel heel bekendt is in Lubliana en waar in Lubliana, die metestrovinie, waar we gaan passeren, is het meer van blet. Het meer van blet is eigenlijk een heel groot meer, heel bekendt ook wel, dus het zal er ook wel etypizie drücker zijn. En, want daarom, reizen we dan weiner naar krawasie. En die is dat we een krawasie gaan doen sind de pletfeetschmieren. Al weet ik niet zo heel goed of dat we echt wel pletfeetsch zijn. We zijn een hele mooie blouwe mieren met waterwallen, waar je ook moet eens erberen om de laart tot en gaan egen. Dat is wel een beetje specieaal. We gaan nog eens een liedjezingen en egen dagr aan een krawasiekertje hier toch wel dicht bij de lichtjes van de schelden. En, een versie van Sarah Bettens als een hele land misschien niet horen. En, wat is wel een hele feene versie Sarah Bettens en dan en, wat dat eigenlijk al wintigste nu niet hier op Spotify. Ik heb nog nog eens ebidjes zoeken of misschien pas uit toch niet Sarah Bettens. Haha. De lichtjes van de schelden. We nemen gewoon een versie en we zingen gewoon en we zingen gewoon een volant. Het is een hele we klaar over een echte kostikers uit welkje. En, en, 하, homm, verkeis, heteron amplifier. Eigen Gerg, filen, marbelent crisarnish cái limbaanen, kar ghee, En dan komik nahr hiz, dan ze lew el kander wir sprik. Duz dit is de laatste priftieki ischref, kijk sa vums margut in de krant. Dan metje prussis war ik pen en ik blef, For da dik weertrich kom in klant. Siegte lich ischref, kijk sa vums margut in klant. Dan metje prussis, kijk sa vums margut in klant. Ich weertrich kom in klant. En datje an de kaiselt staan, Siegte lich ischref, kijk sa vums margut in klant. Die soweken jogen kijk, Die soweken jogen kijk, die soweken jogen kijk, Die soweken jogen kijk, die soweken jogen kijk, Na na na na na na na na na na na na na na na na 12. Schatt, dan ik veel van je hao Dat hoef ik je niet te verklaren En zeh man is toll op z'n kenderen en vrao Maar toch wil ei alteid weer waren Maar heeft somst du zeh Its verkeerts met me vor En kreig ik vor goetavere Denk dan en ons kenderen en slajr dor Maarts brek ga ar dan dik wil svan mei Ziek te lich is van des gelde Dann gaat m'n hart wat sneller slam Ik weet dat jij op mij z'n't watten En dat je aan de keizelstam Ziek te lich is van des gelde Isto wekin ja hoge keik Die me heel wil lief's vertellen Dan ben i chazen prins opren Four мыz iset voe hij eina Vàm vienenne n-u Wat hoaf La niersjped i s sslab",
        "language": "la",
        "segments": [
          {
            "start": 0.0,
            "end": 4.58,
            "text": "A hallo alemaal, en elkom beide zoomer podcast."
          },
          {
            "start": 5.5,
            "end": 9.6,
            "text": "Ikka i vambag startet metven lijitisini."
          },
          {
            "start": 10.22,
            "end": 14.98,
            "text": "En lijitje van pomlin des enetis o plas."
          },
          {
            "start": 24.919999999999998,
            "end": 31.06,
            "text": "Ik heb zante min zakkenen, vinten min haarde hopte ik had,"
          },
          {
            "start": 31.5,
            "end": 35.28,
            "text": "hangt goed tan alkaer ik moet ter gedur zetten,"
          },
          {
            "start": 35.84,
            "end": 37.98,
            "text": "mij als is zerswar van."
          },
          {
            "start": 40.980000000000004,
            "end": 45.4,
            "text": "Ik had watergevangenende kom van mijn hand,"
          },
          {
            "start": 45.68,
            "end": 49.98,
            "text": "ik pracht het naar zee, ik swam terug naar land tot stukje,"
          },
          {
            "start": 50.66,
            "end": 53.98,
            "text": "woerstukje, deke slijn veranderd."
          },
          {
            "start": 56.64,
            "end": 60.74,
            "text": "Jij zij dat het klaar was, numde mije aadlass,"
          },
          {
            "start": 61.24,
            "end": 63.98,
            "text": "sorry dat ik jano op handen draag."
          },
          {
            "start": 64.22,
            "end": 68.78,
            "text": "Jij doet of het niks was, kapt er veel maar vakt dat,"
          },
          {
            "start": 69.2,
            "end": 72.42,
            "text": "galt je bent complex, maar nog hepe kraak."
          },
          {
            "start": 72.78,
            "end": 76.36,
            "text": "De zik weer kopt me spullen, bouheisen van karton."
          },
          {
            "start": 76.9,
            "end": 80.24,
            "text": "De preisie ik betaal om te denken dat het kon."
          },
          {
            "start": 81.06,
            "end": 84.58,
            "text": "Ik wist dat het zwaar was, niet dat het niet waar,"
          },
          {
            "start": 84.86,
            "end": 90.14,
            "text": "was je wereld op mijn schouders, nooit andersom, nooit andersom."
          },
          {
            "start": 97.02,
            "end": 101.26,
            "text": "Jij had, een plok kan je wénje, wist niet dat ik er was,"
          },
          {
            "start": 101.68,
            "end": 106.6,
            "text": "drog mij door de moder daarna, brog ik wat er op je porst,"
          },
          {
            "start": 106.66,
            "end": 110.36,
            "text": "lag je stuin op plaats voor mij, ik wist dat het goed ging komen,"
          },
          {
            "start": 110.7,
            "end": 112.3,
            "text": "toen was het moment voor mij."
          },
          {
            "start": 113.12,
            "end": 116.22,
            "text": "Jij zij dat het klaar was, numde mije aadlass,"
          },
          {
            "start": 117.24,
            "end": 120.46,
            "text": "sorry dat ik jano op handen draag."
          },
          {
            "start": 120.46,
            "end": 124.8,
            "text": "Jij doet of het niks was, kapt er veel maar vakt dat,"
          },
          {
            "start": 125.2,
            "end": 128.42,
            "text": "galt je bent complex, maar nog hepe kraak."
          },
          {
            "start": 128.78,
            "end": 132.3,
            "text": "De zik weer kopt me spullen, bouheisen van karton."
          },
          {
            "start": 132.94,
            "end": 136.3,
            "text": "De preisie ik betaal om te denken dat het kon."
          },
          {
            "start": 137.1,
            "end": 140.58,
            "text": "Ik wist dat het zwaar was, niet dat het niet waar,"
          },
          {
            "start": 140.68,
            "end": 146.46,
            "text": "was je wereld op mijn schouders, nooit andersom, nooit andersom,"
          },
          {
            "start": 146.46,
            "end": 151.06,
            "text": "niet waar, ik was weken reelebrand, kweeleweld, koseke,"
          },
          {
            "start": 151.5,
            "end": 152.78,
            "text": "te veel gevraagd."
          },
          {
            "start": 153.4,
            "end": 156.46,
            "text": "Achter afbekeken waren het labieleweken,"
          },
          {
            "start": 157.18,
            "end": 160.8,
            "text": "ik zat bij de binnenbreken, als jij het vraagt,"
          },
          {
            "start": 161.06,
            "end": 164.74,
            "text": "maar jij zij dat het klaar was, numde mije aadlass,"
          },
          {
            "start": 165.3,
            "end": 168.42,
            "text": "sorry dat ik jou nog op handen draag."
          },
          {
            "start": 168.98,
            "end": 172.82,
            "text": "Jij doet of het niks was, kapt er veel maar vakt dat,"
          },
          {
            "start": 172.82,
            "end": 176.56,
            "text": "galt je bent complex, maar nog hepe kraak."
          },
          {
            "start": 176.9,
            "end": 180.26,
            "text": "De zik weer kopt me spullen, bouheisen van karton."
          },
          {
            "start": 180.92,
            "end": 184.32,
            "text": "De preisie ik betaal om te denken dat het kon."
          },
          {
            "start": 185.12,
            "end": 188.56,
            "text": "Ik wist dat het zwaar was, niet dat het niet waar,"
          },
          {
            "start": 188.64,
            "end": 194.5,
            "text": "was je wereld op mijn schouders, nooit andersom, nooit andersom."
          },
          {
            "start": 195.58,
            "end": 198.92,
            "text": "Zodat, dat was het liedje van pomelintes adlass."
          },
          {
            "start": 198.92,
            "end": 204.92,
            "text": "Dat is ook de favorite zangeret van ons kleine limeloo."
          },
          {
            "start": 206.34,
            "end": 210.04,
            "text": "Ze vindt de superleuk om dat ze zelf haar gliedeje maakt,"
          },
          {
            "start": 210.56,
            "end": 212.28,
            "text": "omdat ze zelf haar teksten maakt."
          },
          {
            "start": 213.04,
            "end": 214.86,
            "text": "Ik ga ook heel veel van poezie,"
          },
          {
            "start": 215.54,
            "end": 222.66,
            "text": "en ik ga jullie ebidjes een gedicht voordragen van ton hermans"
          },
          {
            "start": 222.66,
            "end": 226.26,
            "text": "en dat gedichte et de z."
          },
          {
            "start": 228.5,
            "end": 230.14,
            "text": "Ik wil alleen zijn met de z."
          },
          {
            "start": 230.94,
            "end": 232.78,
            "text": "Ik wil alleen zijn met het strand."
          },
          {
            "start": 233.92,
            "end": 237.9,
            "text": "Ik wil me ziel wat laten waren, niet me lijven me verstand."
          },
          {
            "start": 239.1,
            "end": 241.02,
            "text": "Ik wil gewoon een beetje dromen,"
          },
          {
            "start": 241.74,
            "end": 243.96,
            "text": "rond de dingen die ik voel en de z."
          },
          {
            "start": 244.44,
            "end": 247.72,
            "text": "Ik weet het zeker dat ze weet wat ik betoel."
          },
          {
            "start": 248.66,
            "end": 251.86,
            "text": "Ik wil alleen zijn met de golven, ik wil alleen zijn met de lucht."
          },
          {
            "start": 251.86,
            "end": 254.18,
            "text": "Ik wil luister naar mijn abem,"
          },
          {
            "start": 254.6,
            "end": 255.94,
            "text": "ik wil luister naar mijn z."
          },
          {
            "start": 256.44,
            "end": 258.9,
            "text": "Ik wil luister naar mijn zwijgen,"
          },
          {
            "start": 259.8,
            "end": 261.26,
            "text": "daarna zal ik vergaan."
          },
          {
            "start": 261.86,
            "end": 262.46,
            "text": "En de z."
          },
          {
            "start": 262.84,
            "end": 264.34,
            "text": "Ik weet het zeker,"
          },
          {
            "start": 265.24,
            "end": 267.1,
            "text": "zal mijn zwijgen wel verstaan."
          },
          {
            "start": 268.42,
            "end": 272.18,
            "text": "Ton hermans schrijft hele mooie gedichter,"
          },
          {
            "start": 272.92,
            "end": 275.0,
            "text": "heel fijn, heel poeitis."
          },
          {
            "start": 276.3,
            "end": 279.56,
            "text": "En andere Nederlandse dichter die ik ook al heel fijn vind,"
          },
          {
            "start": 279.56,
            "end": 281.46,
            "text": "en ik wil ook hele tofel boekersgericht is,"
          },
          {
            "start": 281.88,
            "end": 283.12,
            "text": "en ik wil hem geen schmitt."
          },
          {
            "start": 283.64,
            "end": 285.84,
            "text": "En ik wil eens graag eeweljes boer,"
          },
          {
            "start": 286.22,
            "end": 288.32,
            "text": "de regenworm en zijn moeder."
          },
          {
            "start": 289.28,
            "end": 292.34,
            "text": "Er was een regenworm in snake,"
          },
          {
            "start": 292.92,
            "end": 295.36,
            "text": "die altijd naar de sterkeek"
          },
          {
            "start": 295.36,
            "end": 297.02,
            "text": "en vluisterde,"
          },
          {
            "start": 297.68,
            "end": 300.48,
            "text": "hoes schoon, hoes schoon."
          },
          {
            "start": 301.46,
            "end": 302.4,
            "text": "Zij moeder zei,"
          },
          {
            "start": 302.82,
            "end": 303.88,
            "text": "oh, toet toch gewoon!"
          },
          {
            "start": 304.62,
            "end": 306.36,
            "text": "Kijk naar beneden naar de grond,"
          },
          {
            "start": 306.98,
            "end": 307.94,
            "text": "dat is normal,"
          },
          {
            "start": 307.94,
            "end": 309.54,
            "text": "dat is gezond."
          },
          {
            "start": 310.52,
            "end": 311.42,
            "text": "Kijk naar beneden,"
          },
          {
            "start": 311.72,
            "end": 312.32,
            "text": "zoals ik."
          },
          {
            "start": 313.66,
            "end": 314.04,
            "text": "En toen,"
          },
          {
            "start": 315.1,
            "end": 317.36,
            "text": "toen kwam de leberk."
          },
          {
            "start": 318.56,
            "end": 321.24,
            "text": "Het wormpje dat naar boven staden,"
          },
          {
            "start": 322.02,
            "end": 322.96,
            "text": "zag hem op tijd,"
          },
          {
            "start": 323.72,
            "end": 324.88,
            "text": "een grob in daar."
          },
          {
            "start": 325.66,
            "end": 327.86,
            "text": "Maar moeder naar beneden kijk,"
          },
          {
            "start": 328.84,
            "end": 330.54,
            "text": "werd opgegeten,"
          },
          {
            "start": 331.18,
            "end": 332.5,
            "text": "daar in snake."
          },
          {
            "start": 333.68,
            "end": 335.58,
            "text": "Dus doe nooit wat je moeder zei."
          },
          {
            "start": 336.58,
            "end": 340.06,
            "text": "Dan komt het allemaal wel tijd."
          },
          {
            "start": 341.5,
            "end": 341.96,
            "text": "Heel,"
          },
          {
            "start": 342.2,
            "end": 342.9,
            "text": "vrij vol,"
          },
          {
            "start": 343.12,
            "end": 344.76,
            "text": "heel grappig ook allemaal."
          },
          {
            "start": 345.68,
            "end": 349.2,
            "text": "Ik wil wel nog rustisch eewetjes een liedje singen."
          },
          {
            "start": 349.7,
            "end": 351.42,
            "text": "Ik ga een liedje singen"
          },
          {
            "start": 351.42,
            "end": 353.38,
            "text": "van een zangeres."
          },
          {
            "start": 353.74,
            "end": 357.5,
            "text": "En die zangeres heet eeva de roveren"
          },
          {
            "start": 357.5,
            "end": 359.2,
            "text": "in bellische zangeres."
          },
          {
            "start": 359.78,
            "end": 361.74,
            "text": "Maar een heel groot"
          },
          {
            "start": 362.58,
            "end": 363.6,
            "text": "repert waren."
          },
          {
            "start": 363.6,
            "end": 365.54,
            "text": "En ik ga een liedje singen"
          },
          {
            "start": 365.54,
            "end": 368.0,
            "text": "en laat m'er je liedzin."
          },
          {
            "start": 379.88,
            "end": 382.26,
            "text": "Eewetjes een instrumentalstakje."
          },
          {
            "start": 383.22,
            "end": 386.02,
            "text": "En komt er zo meteen aam."
          },
          {
            "start": 388.88000000000005,
            "end": 391.02,
            "text": "Ik zit in over alle lei"
          },
          {
            "start": 391.88,
            "end": 394.06,
            "text": "en over iedereen."
          },
          {
            "start": 396.04,
            "end": 397.98,
            "text": "Maar nooit is over mij."
          },
          {
            "start": 399.9,
            "end": 402.0,
            "text": "Maar al te vaak glijd op."
          },
          {
            "start": 403.02,
            "end": 404.42,
            "text": "Wij al zo verkopen."
          },
          {
            "start": 405.76,
            "end": 408.9,
            "text": "En hoe jij dat beschrijft."
          },
          {
            "start": 409.94,
            "end": 411.84,
            "text": "Bien idee je meer"
          },
          {
            "start": 411.84,
            "end": 414.22,
            "text": "of krijg je het niet gezegd."
          },
          {
            "start": 414.22,
            "end": 416.16,
            "text": "Bij je fantasie"
          },
          {
            "start": 416.16,
            "end": 418.96,
            "text": "maar dan levens echt."
          },
          {
            "start": 420.48,
            "end": 421.98,
            "text": "Laat m'er jou liedzin."
          },
          {
            "start": 423.0,
            "end": 425.16,
            "text": "Geef bij een zine jourenfriend."
          },
          {
            "start": 425.72,
            "end": 427.42,
            "text": "Ik wacht al zo lang."
          },
          {
            "start": 428.14,
            "end": 429.52,
            "text": "Wat nu geen tijd?"
          },
          {
            "start": 430.84,
            "end": 432.46,
            "text": "Laat m'er liedzin."
          },
          {
            "start": 433.24,
            "end": 435.78,
            "text": "M'n stroven over een rijmaarik."
          },
          {
            "start": 436.56,
            "end": 437.6,
            "text": "Gelukkig zijn."
          },
          {
            "start": 440.48,
            "end": 444.62,
            "text": "Met een enkelhoort."
          },
          {
            "start": 453.54,
            "end": 456.3,
            "text": "Vrienden zeggen mij altijd."
          },
          {
            "start": 457.44,
            "end": 459.0,
            "text": "Je bent maar plogiat."
          },
          {
            "start": 460.76,
            "end": 463.26,
            "text": "Je maakt jezelf wat wij's."
          },
          {
            "start": 464.26,
            "end": 467.5,
            "text": "Maar ik geloven mij gevoel."
          },
          {
            "start": 467.86,
            "end": 469.54,
            "text": "En niet een goeie rant."
          },
          {
            "start": 471.38,
            "end": 474.24,
            "text": "Ik heb maar een doel."
          },
          {
            "start": 474.9,
            "end": 476.68,
            "text": "Krijg je me niet op papier."
          },
          {
            "start": 477.0,
            "end": 478.7,
            "text": "Ik help je graag op weg."
          },
          {
            "start": 479.52,
            "end": 481.24,
            "text": "Jeik ben je fantasie."
          },
          {
            "start": 481.66,
            "end": 483.8,
            "text": "Maar dan levens echt."
          },
          {
            "start": 485.16,
            "end": 486.82,
            "text": "Laat m'er jou liedzin."
          },
          {
            "start": 487.9,
            "end": 490.1,
            "text": "Geef bij een zine jourenfriend."
          },
          {
            "start": 490.1,
            "end": 492.4,
            "text": "Ik wacht al zo lang."
          },
          {
            "start": 492.76,
            "end": 494.38,
            "text": "Wat nu geen tijd?"
          },
          {
            "start": 495.56,
            "end": 497.3,
            "text": "Laat m'er jou liedzin."
          },
          {
            "start": 497.9,
            "end": 498.76,
            "text": "Geef bij een zine jourenfriend."
          },
          {
            "start": 498.76,
            "end": 500.8,
            "text": "M'n stroven over een rijmaarik."
          },
          {
            "start": 501.3,
            "end": 502.6,
            "text": "Gelukkig zijn."
          },
          {
            "start": 505.92,
            "end": 510.96,
            "text": "Met een enkelhoort."
          },
          {
            "start": 510.96,
            "end": 517.02,
            "text": "En enkelhoort."
          },
          {
            "start": 523.4,
            "end": 525.9,
            "text": "Heb je geen idee je meer."
          },
          {
            "start": 526.38,
            "end": 528.16,
            "text": "K' help je graag op weg."
          },
          {
            "start": 528.72,
            "end": 530.44,
            "text": "Jeik ben je fantasie."
          },
          {
            "start": 530.96,
            "end": 533.14,
            "text": "Maar dan levens echt."
          },
          {
            "start": 534.54,
            "end": 536.22,
            "text": "Laat m'er jou liedzin."
          },
          {
            "start": 536.88,
            "end": 539.38,
            "text": "Geef bij een zine jourenfriend."
          },
          {
            "start": 539.38,
            "end": 541.54,
            "text": "Ik wacht al zo lang."
          },
          {
            "start": 542.28,
            "end": 543.42,
            "text": "Wat nu geen tijd?"
          },
          {
            "start": 544.9,
            "end": 546.74,
            "text": "Laat m'er jou liedzin."
          },
          {
            "start": 547.14,
            "end": 548.02,
            "text": "Geef bij een zine jourenfriend."
          },
          {
            "start": 548.02,
            "end": 550.04,
            "text": "M'n stroven over een rijmaarik."
          },
          {
            "start": 550.6,
            "end": 552.26,
            "text": "Gelukkig zijn."
          },
          {
            "start": 555.0600000000001,
            "end": 557.02,
            "text": "Laat m'er jou liedzin."
          },
          {
            "start": 557.58,
            "end": 560.2,
            "text": "Geef bij een zine jourenfriend."
          },
          {
            "start": 560.68,
            "end": 562.76,
            "text": "Ik wacht al zo lang."
          },
          {
            "start": 563.14,
            "end": 564.86,
            "text": "Wat nu geen tijd?"
          },
          {
            "start": 565.56,
            "end": 567.38,
            "text": "Laat m'er jou liedzin."
          },
          {
            "start": 567.38,
            "end": 569.92,
            "text": "Geef bij een zine jourenfriend."
          },
          {
            "start": 571.16,
            "end": 572.84,
            "text": "Gelukkig zijn."
          },
          {
            "start": 574.16,
            "end": 579.68,
            "text": "Met een en enkelhoort."
          },
          {
            "start": 580.44,
            "end": 586.24,
            "text": "Dat was het liedje van de roveren."
          },
          {
            "start": 587.1,
            "end": 588.58,
            "text": "We hadden een verder."
          },
          {
            "start": 589.06,
            "end": 590.88,
            "text": "K' eik kijkert eikertje nog."
          },
          {
            "start": 590.88,
            "end": 596.48,
            "text": "Ik dacht dat ik een heel leuk gedichtje wel is."
          },
          {
            "start": 596.88,
            "end": 598.1,
            "text": "Ik wilde het lieje."
          },
          {
            "start": 600.38,
            "end": 602.1,
            "text": "Bijvoorbeeld een kwot."
          },
          {
            "start": 602.32,
            "end": 603.56,
            "text": "Dat is ook wel heel fein."
          },
          {
            "start": 604.1,
            "end": 606.2,
            "text": "Een kwot is wel zo."
          },
          {
            "start": 606.76,
            "end": 609.1,
            "text": "Het land is warm, de weg is wet."
          },
          {
            "start": 610.12,
            "end": 612.66,
            "text": "Het duin is leeg, de zeen stil."
          },
          {
            "start": 613.46,
            "end": 615.8,
            "text": "De zon is grijs, de dag is heel."
          },
          {
            "start": 616.3800000000001,
            "end": 618.28,
            "text": "Dat was een heel speciaal kwot."
          },
          {
            "start": 618.76,
            "end": 621.94,
            "text": "Een keer die ik nu niet zelf zou kiezen."
          },
          {
            "start": 622.6,
            "end": 624.48,
            "text": "Ik heb het ook kwot, dus wel stoet schek."
          },
          {
            "start": 624.84,
            "end": 626.92,
            "text": "Denk iets mooi, zeg iets liefs."
          },
          {
            "start": 627.6,
            "end": 630.26,
            "text": "Dan heeft elke dag iets positiefs."
          },
          {
            "start": 632.8400000000001,
            "end": 636.86,
            "text": "En wist je dat een elskuuken, een ooit zelf,"
          },
          {
            "start": 637.54,
            "end": 638.58,
            "text": "eerste en eil was?"
          },
          {
            "start": 639.48,
            "end": 642.2,
            "text": "Elke wijze uel broed in een nest op een toekomst."
          },
          {
            "start": 643.2,
            "end": 646.12,
            "text": "Mama Eil leegd liefde vol in haar ei en toekomst."
          },
          {
            "start": 646.94,
            "end": 649.24,
            "text": "Mama Eil broed in een nest op een ei."
          },
          {
            "start": 649.96,
            "end": 654.9,
            "text": "En elke wijze uel was ooit zelf, eerste en eil skuuken."
          },
          {
            "start": 656.1,
            "end": 656.76,
            "text": "Mooi ha."
          },
          {
            "start": 658.46,
            "end": 661.5,
            "text": "Goed, twar overig, gaan we nog ebukjes praten."
          },
          {
            "start": 661.78,
            "end": 665.28,
            "text": "Ik ga misschien ebukjes een krante artikel te leren,"
          },
          {
            "start": 665.28,
            "end": 671.62,
            "text": "maar vandaag zijn we zatterdag 12 juli."
          },
          {
            "start": 673.2,
            "end": 675.84,
            "text": "Als er een limme opkamp vertrokken met hero,"
          },
          {
            "start": 675.98,
            "end": 678.4,
            "text": "die ze lene artikel twingen, vertrokken."
          },
          {
            "start": 678.92,
            "end": 681.2,
            "text": "Morgen vertrekts el jappen opkamp,"
          },
          {
            "start": 681.48,
            "end": 682.68,
            "text": "hij vertrekte op hockeykamp,"
          },
          {
            "start": 683.32,
            "end": 688.08,
            "text": "en haar bros gaat naar de hockeyclub draven."
          },
          {
            "start": 688.78,
            "end": 690.58,
            "text": "Hij had daar met sportways."
          },
          {
            "start": 694.2,
            "end": 695.98,
            "text": "Op hockeykamp worden aantal dagen."
          },
          {
            "start": 696.64,
            "end": 698.9,
            "text": "Wat gaan we ebukjes lezen?"
          },
          {
            "start": 698.9,
            "end": 701.08,
            "text": "Ik zit hier op het nieuwsplatz."
          },
          {
            "start": 702.66,
            "end": 705.04,
            "text": "We gaan ebukjes zoeken,"
          },
          {
            "start": 705.14,
            "end": 709.1,
            "text": "wat er interessant is om te lezen."
          },
          {
            "start": 709.4,
            "end": 713.48,
            "text": "Er staat ook altijd heel veel komkommer nieuws op."
          },
          {
            "start": 714.56,
            "end": 716.6,
            "text": "Het is ook om te komen op artit."
          },
          {
            "start": 718.22,
            "end": 721.56,
            "text": "Dus ik zoek wel iets leuk om te lezen,"
          },
          {
            "start": 721.8,
            "end": 724.3,
            "text": "iets tak zelf ook graven lezen,"
          },
          {
            "start": 725.24,
            "end": 726.56,
            "text": "iets tak nog niet weet."
          },
          {
            "start": 727.56,
            "end": 729.0,
            "text": "Er staan natuurlijk veel opkamp,"
          },
          {
            "start": 729.0,
            "end": 733.8,
            "text": "maar we gaan ebukje opkamp,"
          },
          {
            "start": 734.56,
            "end": 735.7,
            "text": "over Trump,"
          },
          {
            "start": 735.98,
            "end": 740.28,
            "text": "en dat is een beetje tegen."
          },
          {
            "start": 740.96,
            "end": 743.06,
            "text": "Ik zie hier dat er vandaag."
          },
          {
            "start": 744.2,
            "end": 748.62,
            "text": "Een zoek-accit was aan de ze naar een keetje."
          },
          {
            "start": 748.88,
            "end": 749.8,
            "text": "Ik ga ebukje lezen."
          },
          {
            "start": 750.8,
            "end": 753.18,
            "text": "Zoek-accit met boten en helikopters"
          },
          {
            "start": 753.18,
            "end": 756.46,
            "text": "naar vermist keentje bleikt valsallaren."
          },
          {
            "start": 757.24,
            "end": 758.94,
            "text": "Aan de kust van de banen"
          },
          {
            "start": 758.94,
            "end": 760.44,
            "text": "zogtende hulpdiensten"
          },
          {
            "start": 760.44,
            "end": 763.98,
            "text": "sind 16 ur naar een keentje van 5 jaar."
          },
          {
            "start": 764.72,
            "end": 768.08,
            "text": "Uiteindelijk bleek het om een valsallaren te gaan."
          },
          {
            "start": 768.88,
            "end": 770.88,
            "text": "Ratters speurde zij aan zij"
          },
          {
            "start": 770.88,
            "end": 773.14,
            "text": "met boten uit water op ervlak af"
          },
          {
            "start": 773.14,
            "end": 775.14,
            "text": "en ook brandweer Westhoek"
          },
          {
            "start": 775.14,
            "end": 777.94,
            "text": "post oost deunkerke werd opgroepen."
          },
          {
            "start": 777.94,
            "end": 780.16,
            "text": "Ook de helikopter werd ingezet."
          },
          {
            "start": 780.82,
            "end": 783.32,
            "text": "Eindelijk bleek het om valsallaren te gaan."
          },
          {
            "start": 784.02,
            "end": 786.04,
            "text": "Een strandganger dacht dat zij een drinken"
          },
          {
            "start": 786.04,
            "end": 787.24,
            "text": "in had gezien in ze"
          },
          {
            "start": 787.94,
            "end": 788.96,
            "text": "en melde rattanderhiders,"
          },
          {
            "start": 789.46,
            "end": 790.62,
            "text": "zeg in Helijn Engels,"
          },
          {
            "start": 791.2,
            "end": 793.52,
            "text": "woordhoerster van polisizone Westpust."
          },
          {
            "start": 794.34,
            "end": 796.14,
            "text": "Er was de sprake van een keentje,"
          },
          {
            "start": 796.34,
            "end": 797.28,
            "text": "maar dat kloppt niet."
          },
          {
            "start": 798.02,
            "end": 800.26,
            "text": "Er werd een groot schaalige zoek-accit opgestart,"
          },
          {
            "start": 800.52,
            "end": 802.14,
            "text": "maar er werd niemand gevonden."
          },
          {
            "start": 802.98,
            "end": 806.94,
            "text": "Na ruim een ure is die zoek-accit dan ook stopgidets."
          },
          {
            "start": 807.94,
            "end": 809.22,
            "text": "Een duur grappie,"
          },
          {
            "start": 809.52,
            "end": 810.54,
            "text": "denk ik dan,"
          },
          {
            "start": 810.8,
            "end": 811.46,
            "text": "maar ik wil ookig"
          },
          {
            "start": 811.46,
            "end": 814.38,
            "text": "is er niemand over te gaan."
          },
          {
            "start": 815.34,
            "end": 816.76,
            "text": "We gaan nog eens even just"
          },
          {
            "start": 816.76,
            "end": 818.28,
            "text": "een liedje singen."
          },
          {
            "start": 819.2800000000001,
            "end": 821.4,
            "text": "Ik wil je dat in het niederland singen,"
          },
          {
            "start": 821.44,
            "end": 822.56,
            "text": "dus ik ben even just aan het denken."
          },
          {
            "start": 823.38,
            "end": 825.72,
            "text": "Ik wil wel eens een liedje linge van Mira."
          },
          {
            "start": 826.38,
            "end": 829.92,
            "text": "Mira is een moderne kleinkunst."
          },
          {
            "start": 832.2800000000001,
            "end": 833.16,
            "text": "Zeg heeft"
          },
          {
            "start": 834.22,
            "end": 836.68,
            "text": "niet zo heel veel nummers"
          },
          {
            "start": 836.68,
            "end": 838.3,
            "text": "die bekend zijn,"
          },
          {
            "start": 838.54,
            "end": 840.3,
            "text": "maar eetje daarvan die keerleuk."
          },
          {
            "start": 840.68,
            "end": 842.46,
            "text": "Zeg een grenzen."
          },
          {
            "start": 842.78,
            "end": 844.24,
            "text": "Grenzen van Mira."
          },
          {
            "start": 844.84,
            "end": 847.5,
            "text": "We gaan nog eens singen."
          },
          {
            "start": 854.26,
            "end": 857.38,
            "text": "Kan mijn grenzen niet?"
          },
          {
            "start": 858.16,
            "end": 861.34,
            "text": "Ik kan mijn grenzen niet."
          },
          {
            "start": 861.96,
            "end": 865.2,
            "text": "Grenzen zijn voor mensen die."
          },
          {
            "start": 865.2,
            "end": 868.44,
            "text": "Nie weten waar naartoe."
          },
          {
            "start": 882.0600000000001,
            "end": 885.48,
            "text": "Ik ben toerisch tent leven"
          },
          {
            "start": 886.2,
            "end": 889.84,
            "text": "noot lang hergesgebleven."
          },
          {
            "start": 890.68,
            "end": 893.44,
            "text": "Mijn idee over wat moet en wat mag"
          },
          {
            "start": 893.44,
            "end": 897.6,
            "text": "verander van dag op dag."
          },
          {
            "start": 898.68,
            "end": 900.62,
            "text": "O, wat een feest."
          },
          {
            "start": 902.34,
            "end": 904.74,
            "text": "O, wat een feest."
          },
          {
            "start": 905.98,
            "end": 909.38,
            "text": "Ik kan mijn grenzen niet."
          },
          {
            "start": 909.9,
            "end": 913.42,
            "text": "Ik kan mijn grenzen niet."
          },
          {
            "start": 914.1,
            "end": 917.32,
            "text": "Grenzen zijn voor mensen die."
          },
          {
            "start": 917.84,
            "end": 920.22,
            "text": "Nie weten waar naartoe."
          },
          {
            "start": 921.8000000000001,
            "end": 924.22,
            "text": "Ik weet dat zo goed."
          },
          {
            "start": 930.36,
            "end": 933.38,
            "text": "Mijn vol duizend man."
          },
          {
            "start": 934.68,
            "end": 937.48,
            "text": "Mijn meenig meenig vrou."
          },
          {
            "start": 938.62,
            "end": 941.58,
            "text": "Dus wat neer jij zegt."
          },
          {
            "start": 942.66,
            "end": 945.48,
            "text": "O, schalt ik al van jou."
          },
          {
            "start": 946.2,
            "end": 948.36,
            "text": "Ik mij af van wie."
          },
          {
            "start": 948.36,
            "end": 952.46,
            "text": "Vraag ik mij af van wie."
          },
          {
            "start": 954.14,
            "end": 957.36,
            "text": "Ik kan mijn grenzen niet."
          },
          {
            "start": 957.92,
            "end": 961.4,
            "text": "Ik kan mijn grenzen niet."
          },
          {
            "start": 962.18,
            "end": 965.26,
            "text": "Grenzen zijn voor mensen die."
          },
          {
            "start": 965.76,
            "end": 968.34,
            "text": "Nie weten waar naartoe."
          },
          {
            "start": 969.76,
            "end": 978.04,
            "text": "Ik weet dat zo goed."
          },
          {
            "start": 979.56,
            "end": 981.88,
            "text": "Dan haven en hartzoek."
          },
          {
            "start": 982.08,
            "end": 983.9,
            "text": "Dan haven en hartzoek."
          },
          {
            "start": 987.34,
            "end": 989.48,
            "text": "Op een dag plak ik."
          },
          {
            "start": 989.9,
            "end": 993.4,
            "text": "Plak ik mijn grenzen af."
          },
          {
            "start": 1001.32,
            "end": 1005.4,
            "text": "Ik kan mijn grenzen niet."
          },
          {
            "start": 1005.9,
            "end": 1009.4,
            "text": "Ik kan mijn grenzen niet."
          },
          {
            "start": 1010.04,
            "end": 1013.34,
            "text": "Grenzen zijn voor mensen die."
          },
          {
            "start": 1013.9,
            "end": 1016.36,
            "text": "Nie weten waar naartoe."
          },
          {
            "start": 1018.76,
            "end": 1021.38,
            "text": "Ik kan mijn grenzen niet."
          },
          {
            "start": 1022.2,
            "end": 1025.28,
            "text": "Ik kan mijn grenzen niet."
          },
          {
            "start": 1025.28,
            "end": 1029.28,
            "text": "Grenzen zijn voor mensen die."
          },
          {
            "start": 1029.98,
            "end": 1032.22,
            "text": "Nie weten waar naartoe."
          },
          {
            "start": 1034.46,
            "end": 1037.22,
            "text": "En ik weet dat zo goed."
          },
          {
            "start": 1038.32,
            "end": 1041.1,
            "text": "En ik weet dat zo goed."
          },
          {
            "start": 1043.44,
            "end": 1046.44,
            "text": "Dat was et litje van mida."
          },
          {
            "start": 1047.24,
            "end": 1051.62,
            "text": "Als vervolger op etjes en een heel mooi kredichtje lesen."
          },
          {
            "start": 1051.62,
            "end": 1055.42,
            "text": "En het gedichtje gaat over mooie momenten."
          },
          {
            "start": 1056.8,
            "end": 1058.78,
            "text": "Soms zou ik de tijd willen vangen."
          },
          {
            "start": 1059.62,
            "end": 1062.26,
            "text": "Mijn mooiste momenten zorgvildig bewaardt."
          },
          {
            "start": 1062.98,
            "end": 1064.56,
            "text": "Met liefte, verzameld."
          },
          {
            "start": 1065.18,
            "end": 1065.98,
            "text": "Strikje eron."
          },
          {
            "start": 1066.98,
            "end": 1069.98,
            "text": "Al mijn fijne herinneringen dicht bij elkaar."
          },
          {
            "start": 1071.42,
            "end": 1073.28,
            "text": "En dat ik dan soms op een avond."
          },
          {
            "start": 1073.86,
            "end": 1075.74,
            "text": "Nog ebiedjes terug kan naartoe."
          },
          {
            "start": 1075.74,
            "end": 1080.76,
            "text": "Dat ik die mooiste momenten gewone naartoe dan kan."
          },
          {
            "start": 1081.74,
            "end": 1083.08,
            "text": "Zo maar nog eens opnie van."
          },
          {
            "start": 1084.0,
            "end": 1085.44,
            "text": "Wat fein is."
          },
          {
            "start": 1086.22,
            "end": 1087.14,
            "text": "Wat mooi was."
          },
          {
            "start": 1087.94,
            "end": 1090.14,
            "text": "Is nooit echt over of klaar."
          },
          {
            "start": 1091.04,
            "end": 1096.92,
            "text": "Als ik het heel vervolg met een strik eron bewaardt."
          },
          {
            "start": 1097.78,
            "end": 1098.42,
            "text": "Mooie."
          },
          {
            "start": 1099.22,
            "end": 1101.18,
            "text": "Ja, vind ik wel een mooie gedichtje."
          },
          {
            "start": 1101.18,
            "end": 1106.5,
            "text": "En het gedichtje over mooie momenten uit klopt ook wel een klein beetje."
          },
          {
            "start": 1107.1,
            "end": 1111.54,
            "text": "Als het wel onwisfein zijn om er toch nog eens eeudjes naartoe te mogen."
          },
          {
            "start": 1112.14,
            "end": 1115.36,
            "text": "Dus naar een mooi momenten."
          },
          {
            "start": 1115.36,
            "end": 1117.16,
            "text": "Of eens eeudjes terug in de tijd staan."
          },
          {
            "start": 1118.5,
            "end": 1119.06,
            "text": "Fein."
          },
          {
            "start": 1119.76,
            "end": 1120.02,
            "text": "Ho!"
          },
          {
            "start": 1122.72,
            "end": 1125.8,
            "text": "Ben de kort gaan we ook op reis naar krowaasje."
          },
          {
            "start": 1125.8,
            "end": 1129.14,
            "text": "We gaan er heel veel dingetjes besoeken."
          },
          {
            "start": 1129.74,
            "end": 1133.02,
            "text": "We vertrekken in zeel uiteraart."
          },
          {
            "start": 1133.32,
            "end": 1137.44,
            "text": "Over de nachtreeren en dan rijden we naar Zell Amzee."
          },
          {
            "start": 1137.84,
            "end": 1141.46,
            "text": "Zell Amzee is een dorpje in Oostrijk."
          },
          {
            "start": 1143.6200000000001,
            "end": 1145.98,
            "text": "Een bekend dorpje."
          },
          {
            "start": 1146.82,
            "end": 1148.14,
            "text": "Het is een skigebied in de winter,"
          },
          {
            "start": 1148.38,
            "end": 1150.68,
            "text": "maar dat er zeven zeer te kermeter biste is."
          },
          {
            "start": 1150.68,
            "end": 1155.66,
            "text": "Maar in de zomer is het ook wel een aanlokselijke plek."
          },
          {
            "start": 1157.86,
            "end": 1161.58,
            "text": "Het meerdataar lecht in Zell Amzee is uiteraart de Zellersie."
          },
          {
            "start": 1162.9,
            "end": 1164.92,
            "text": "En je kan er ook die hele mooie barge zien,"
          },
          {
            "start": 1165.12,
            "end": 1168.62,
            "text": "bijvoorbeeld de kitssteinhoren,"
          },
          {
            "start": 1169.22,
            "end": 1173.06,
            "text": "die 3.29 m hoog is."
          },
          {
            "start": 1174.1,
            "end": 1176.92,
            "text": "Dus gelegend in Kaproen,"
          },
          {
            "start": 1176.92,
            "end": 1179.78,
            "text": "in Zellbach, in Oostrijk."
          },
          {
            "start": 1181.1,
            "end": 1182.06,
            "text": "Zwell is feinig,"
          },
          {
            "start": 1182.14,
            "end": 1183.64,
            "text": "maar ik kijk er wel diewetjes naar uit,"
          },
          {
            "start": 1184.32,
            "end": 1186.86,
            "text": "om diewetjes in de bergen te zijn,"
          },
          {
            "start": 1187.06,
            "end": 1187.8,
            "text": "zoals vroegerige,"
          },
          {
            "start": 1188.6599999999999,
            "end": 1191.32,
            "text": "vroegerige ik altijd op reis naar de bergen om te wandelen."
          },
          {
            "start": 1191.9,
            "end": 1192.54,
            "text": "Dat wandelen,"
          },
          {
            "start": 1192.6,
            "end": 1194.06,
            "text": "dat moet nu niet persi voor mij,"
          },
          {
            "start": 1195.04,
            "end": 1198.46,
            "text": "maar dat nog m'n keer uitzicht van de bergen"
          },
          {
            "start": 1198.46,
            "end": 1200.28,
            "text": "en de rust uit de bergen pruin."
          },
          {
            "start": 1200.78,
            "end": 1202.06,
            "text": "Dat du die, dat is,"
          },
          {
            "start": 1202.76,
            "end": 1204.68,
            "text": "ja dat wil ik wel hege recnochnikieren."
          },
          {
            "start": 1204.68,
            "end": 1207.56,
            "text": "Dus daarna reden we verder"
          },
          {
            "start": 1207.56,
            "end": 1210.96,
            "text": "van Zellansie naar Lubliana."
          },
          {
            "start": 1211.56,
            "end": 1215.12,
            "text": "Lubliana is de hovstad van Slovenie."
          },
          {
            "start": 1216.46,
            "end": 1221.98,
            "text": "Na schet en hele schatige romantice hovstad."
          },
          {
            "start": 1222.7,
            "end": 1224.12,
            "text": "Wat kan je da allemaal tun?"
          },
          {
            "start": 1225.68,
            "end": 1228.34,
            "text": "Lubliana is en van de kleinse hovstieden."
          },
          {
            "start": 1228.88,
            "end": 1230.62,
            "text": "Dus ze heeft niet zo'n hele lange leist"
          },
          {
            "start": 1230.62,
            "end": 1232.36,
            "text": "met bezinsware, giden of highlights,"
          },
          {
            "start": 1232.36,
            "end": 1233.8,
            "text": "maar wel super leuk."
          },
          {
            "start": 1234.9,
            "end": 1237.82,
            "text": "Dus dat's wel tof over a minis te de trip."
          },
          {
            "start": 1239.16,
            "end": 1241.36,
            "text": "Ies sprik datrou is eit als Lubliana,"
          },
          {
            "start": 1242.18,
            "end": 1244.32,
            "text": "als het echt zo'jus moeten zengen Lubliana."
          },
          {
            "start": 1245.8200000000002,
            "end": 1250.18,
            "text": "Ik kan da heel goed met gewoent de voet door de stad."
          },
          {
            "start": 1251.02,
            "end": 1252.54,
            "text": "Ja, dat centrale plein,"
          },
          {
            "start": 1253.16,
            "end": 1254.36,
            "text": "het prezeren squir,"
          },
          {
            "start": 1255.48,
            "end": 1257.2,
            "text": "prezeren of squir"
          },
          {
            "start": 1257.8600000000001,
            "end": 1261.36,
            "text": "is eit gekelemerk door een hele mooie rose,"
          },
          {
            "start": 1261.63,
            "end": 1262.65,
            "text": "de rosekerk,"
          },
          {
            "start": 1263.73,
            "end": 1264.71,
            "text": "die is niet te mist,"
          },
          {
            "start": 1264.85,
            "end": 1267.33,
            "text": "en dat is echt wel een beetje de ontmoetingsplek voor de locals."
          },
          {
            "start": 1268.25,
            "end": 1271.65,
            "text": "En daar komen eigenlijk alles traten van Lubliana samen."
          },
          {
            "start": 1273.23,
            "end": 1274.41,
            "text": "Die ligt daar ook,"
          },
          {
            "start": 1274.81,
            "end": 1276.45,
            "text": "die kerk aan een rivier,"
          },
          {
            "start": 1276.51,
            "end": 1278.41,
            "text": "waar er drie bruggen overlopen."
          },
          {
            "start": 1279.59,
            "end": 1280.67,
            "text": "Die drie bruggen,"
          },
          {
            "start": 1280.75,
            "end": 1284.39,
            "text": "en zei, ook al een touristische trekpleister."
          },
          {
            "start": 1284.97,
            "end": 1286.15,
            "text": "Wat je daar ook kan zien,"
          },
          {
            "start": 1286.39,
            "end": 1288.21,
            "text": "is eit se castel van Lubliana,"
          },
          {
            "start": 1288.6699999999998,
            "end": 1289.69,
            "text": "Lubliana is een ski grat,"
          },
          {
            "start": 1290.37,
            "end": 1291.61,
            "text": "die ligt een beetje hoger,"
          },
          {
            "start": 1291.65,
            "end": 1293.61,
            "text": "om 376 meter."
          },
          {
            "start": 1294.53,
            "end": 1296.15,
            "text": "Ja, dat er een heel mooi uitzicht."
          },
          {
            "start": 1296.57,
            "end": 1298.97,
            "text": "En ik kan maar de rode daken van Lubliana spotten."
          },
          {
            "start": 1299.69,
            "end": 1301.49,
            "text": "Je kak is en of je te voet erart toegraat,"
          },
          {
            "start": 1301.53,
            "end": 1303.07,
            "text": "maar er is ook een lift."
          },
          {
            "start": 1304.45,
            "end": 1305.45,
            "text": "Als je te goed gaat,"
          },
          {
            "start": 1305.61,
            "end": 1307.47,
            "text": "is 20 minutsje stappen"
          },
          {
            "start": 1307.9699999999998,
            "end": 1309.07,
            "text": "en met het liftje,"
          },
          {
            "start": 1309.73,
            "end": 1311.85,
            "text": "kosteert 6 euro heen en teruggevacht."
          },
          {
            "start": 1311.89,
            "end": 1313.75,
            "text": "Zo'n liftje is altijd wel leuk voor de kindjes."
          },
          {
            "start": 1314.31,
            "end": 1315.19,
            "text": "En ook voordem,"
          },
          {
            "start": 1315.19,
            "end": 1315.69,
            "text": "maar wat is wat?"
          },
          {
            "start": 1316.01,
            "end": 1316.97,
            "text": "Het zal wel warm zijn,"
          },
          {
            "start": 1317.75,
            "end": 1319.71,
            "text": "dat in Lubliana."
          },
          {
            "start": 1322.35,
            "end": 1323.89,
            "text": "Wat kan je daar nog doen?"
          },
          {
            "start": 1324.07,
            "end": 1324.77,
            "text": "Je hebt daar ook,"
          },
          {
            "start": 1325.01,
            "end": 1327.57,
            "text": "de hele bekende drakenbrug."
          },
          {
            "start": 1328.33,
            "end": 1330.73,
            "text": "De draken is eigenlijk een beetje het symbol"
          },
          {
            "start": 1331.67,
            "end": 1332.71,
            "text": "van Lubliana."
          },
          {
            "start": 1333.41,
            "end": 1335.03,
            "text": "Hij wakt eigenlijk over de stad"
          },
          {
            "start": 1335.03,
            "end": 1336.59,
            "text": "en over de inwoners"
          },
          {
            "start": 1336.59,
            "end": 1339.39,
            "text": "en zo'n gelieftemne in het castel."
          },
          {
            "start": 1340.35,
            "end": 1342.13,
            "text": "En zo'n zig daar ook wel te goed gedaan,"
          },
          {
            "start": 1342.27,
            "end": 1344.47,
            "text": "hebben mandelijks aan een jonge vrouwe."
          },
          {
            "start": 1344.47,
            "end": 1347.29,
            "text": "En nu is dat hij,"
          },
          {
            "start": 1347.53,
            "end": 1349.25,
            "text": "de stad hij heeft beschermd,"
          },
          {
            "start": 1349.29,
            "end": 1350.61,
            "text": "is altijd ook ook wel eens de stad"
          },
          {
            "start": 1350.61,
            "end": 1351.77,
            "text": "hebben aangevallen."
          },
          {
            "start": 1352.53,
            "end": 1352.85,
            "text": "Maar,"
          },
          {
            "start": 1355.31,
            "end": 1357.23,
            "text": "als het draak over slagen was,"
          },
          {
            "start": 1357.45,
            "end": 1359.13,
            "text": "dan is hij eigenlijk het symbol geworden"
          },
          {
            "start": 1359.13,
            "end": 1362.39,
            "text": "van Lubliana van de stad."
          },
          {
            "start": 1363.03,
            "end": 1363.57,
            "text": "En dus,"
          },
          {
            "start": 1363.95,
            "end": 1366.47,
            "text": "zeen standbeeld staat op de drakenbrug,"
          },
          {
            "start": 1367.25,
            "end": 1367.97,
            "text": "de drakenbrug."
          },
          {
            "start": 1369.81,
            "end": 1372.13,
            "text": "En waar je toch ook nog niet kerk kan"
          },
          {
            "start": 1372.13,
            "end": 1373.61,
            "text": "gaan keken."
          },
          {
            "start": 1375.5700000000002,
            "end": 1377.93,
            "text": "Niet zo ver van Lubliana,"
          },
          {
            "start": 1378.07,
            "end": 1379.79,
            "text": "en je ook het prejudmakasteel,"
          },
          {
            "start": 1379.81,
            "end": 1381.83,
            "text": "dat legt zo egen in de grootse"
          },
          {
            "start": 1383.31,
            "end": 1383.87,
            "text": "maakt."
          },
          {
            "start": 1384.29,
            "end": 1385.85,
            "text": "Je hebt daar ook de grotte van"
          },
          {
            "start": 1385.85,
            "end": 1386.83,
            "text": "bostonia,"
          },
          {
            "start": 1387.61,
            "end": 1390.13,
            "text": "hele mooie grotte met de ruiwstied."
          },
          {
            "start": 1390.65,
            "end": 1392.43,
            "text": "Wat dat ook wel heel bekendt"
          },
          {
            "start": 1392.43,
            "end": 1393.93,
            "text": "is in Lubliana en waar"
          },
          {
            "start": 1393.93,
            "end": 1395.83,
            "text": "in Lubliana, die metestrovinie,"
          },
          {
            "start": 1396.39,
            "end": 1397.41,
            "text": "waar we gaan passeren,"
          },
          {
            "start": 1397.53,
            "end": 1398.51,
            "text": "is het meer van blet."
          },
          {
            "start": 1398.51,
            "end": 1400.57,
            "text": "Het meer van blet is eigenlijk"
          },
          {
            "start": 1400.57,
            "end": 1402.17,
            "text": "een heel groot meer,"
          },
          {
            "start": 1403.8899999999999,
            "end": 1404.99,
            "text": "heel bekendt ook wel,"
          },
          {
            "start": 1405.03,
            "end": 1405.81,
            "text": "dus het zal er ook wel"
          },
          {
            "start": 1407.09,
            "end": 1408.43,
            "text": "etypizie drücker zijn."
          },
          {
            "start": 1409.89,
            "end": 1410.19,
            "text": "En,"
          },
          {
            "start": 1410.27,
            "end": 1410.69,
            "text": "want daarom,"
          },
          {
            "start": 1410.79,
            "end": 1411.83,
            "text": "reizen we dan"
          },
          {
            "start": 1411.83,
            "end": 1414.21,
            "text": "weiner naar krawasie."
          },
          {
            "start": 1414.93,
            "end": 1416.91,
            "text": "En die is dat we een krawasie gaan doen"
          },
          {
            "start": 1416.91,
            "end": 1418.37,
            "text": "sind de pletfeetschmieren."
          },
          {
            "start": 1419.21,
            "end": 1420.47,
            "text": "Al weet ik niet zo heel goed"
          },
          {
            "start": 1420.47,
            "end": 1422.35,
            "text": "of dat we echt wel pletfeetsch zijn."
          },
          {
            "start": 1423.55,
            "end": 1426.15,
            "text": "We zijn een hele mooie blouwe mieren"
          },
          {
            "start": 1426.15,
            "end": 1428.63,
            "text": "met waterwallen,"
          },
          {
            "start": 1429.37,
            "end": 1431.87,
            "text": "waar je ook moet eens erberen om de laart"
          },
          {
            "start": 1431.87,
            "end": 1432.47,
            "text": "tot en gaan egen."
          },
          {
            "start": 1433.15,
            "end": 1434.13,
            "text": "Dat is wel een beetje"
          },
          {
            "start": 1434.13,
            "end": 1435.41,
            "text": "specieaal."
          },
          {
            "start": 1436.75,
            "end": 1438.91,
            "text": "We gaan nog eens een liedjezingen"
          },
          {
            "start": 1438.91,
            "end": 1441.15,
            "text": "en egen dagr aan een krawasiekertje"
          },
          {
            "start": 1441.15,
            "end": 1443.51,
            "text": "hier toch wel dicht bij"
          },
          {
            "start": 1444.15,
            "end": 1446.09,
            "text": "de lichtjes van de schelden."
          },
          {
            "start": 1446.91,
            "end": 1447.45,
            "text": "En,"
          },
          {
            "start": 1448.23,
            "end": 1450.49,
            "text": "een versie van Sarah Bettens"
          },
          {
            "start": 1450.49,
            "end": 1451.87,
            "text": "als een hele land misschien"
          },
          {
            "start": 1451.87,
            "end": 1453.45,
            "text": "niet horen."
          },
          {
            "start": 1453.45,
            "end": 1453.75,
            "text": "En,"
          },
          {
            "start": 1454.45,
            "end": 1455.47,
            "text": "wat is wel"
          },
          {
            "start": 1455.47,
            "end": 1457.51,
            "text": "een hele feene"
          },
          {
            "start": 1457.51,
            "end": 1459.13,
            "text": "versie Sarah Bettens"
          },
          {
            "start": 1459.13,
            "end": 1460.63,
            "text": "en dan"
          },
          {
            "start": 1461.45,
            "end": 1461.65,
            "text": "en,"
          },
          {
            "start": 1462.19,
            "end": 1463.01,
            "text": "wat dat eigenlijk"
          },
          {
            "start": 1463.01,
            "end": 1465.17,
            "text": "al wintigste nu niet"
          },
          {
            "start": 1465.17,
            "end": 1466.85,
            "text": "hier op Spotify."
          },
          {
            "start": 1468.03,
            "end": 1469.25,
            "text": "Ik heb nog nog eens"
          },
          {
            "start": 1469.25,
            "end": 1470.35,
            "text": "ebidjes zoeken"
          },
          {
            "start": 1470.35,
            "end": 1472.95,
            "text": "of misschien pas uit toch niet Sarah Bettens."
          },
          {
            "start": 1473.09,
            "end": 1473.35,
            "text": "Haha."
          },
          {
            "start": 1475.43,
            "end": 1478.89,
            "text": "De lichtjes van de schelden."
          },
          {
            "start": 1480.57,
            "end": 1482.49,
            "text": "We nemen gewoon een versie"
          },
          {
            "start": 1482.49,
            "end": 1483.35,
            "text": "en we zingen gewoon"
          },
          {
            "start": 1483.35,
            "end": 1485.21,
            "text": "en we zingen gewoon een"
          },
          {
            "start": 1485.21,
            "end": 1485.47,
            "text": "volant."
          },
          {
            "start": 1485.89,
            "end": 1486.31,
            "text": "Het is een hele"
          },
          {
            "start": 1486.31,
            "end": 1486.87,
            "text": "we klaar"
          },
          {
            "start": 1486.87,
            "end": 1488.47,
            "text": "over een echte kostikers"
          },
          {
            "start": 1489.39,
            "end": 1490.13,
            "text": "uit"
          },
          {
            "start": 1490.99,
            "end": 1491.73,
            "text": "welkje."
          },
          {
            "start": 1500.37,
            "end": 1501.11,
            "text": "En,"
          },
          {
            "start": 1504.83,
            "end": 1504.83,
            "text": ""
          },
          {
            "start": 1511.73,
            "end": 1512.47,
            "text": "en,"
          },
          {
            "start": 1512.47,
            "end": 1512.47,
            "text": ""
          },
          {
            "start": 1512.47,
            "end": 1512.47,
            "text": ""
          },
          {
            "start": 1512.47,
            "end": 1512.47,
            "text": ""
          },
          {
            "start": 1512.47,
            "end": 1512.47,
            "text": ""
          },
          {
            "start": 1512.47,
            "end": 1512.47,
            "text": ""
          },
          {
            "start": 1512.47,
            "end": 1513.53,
            "text": "하,"
          },
          {
            "start": 1514.47,
            "end": 1516.01,
            "text": "homm,"
          },
          {
            "start": 1526.83,
            "end": 1528.23,
            "text": "verkeis,"
          },
          {
            "start": 1528.23,
            "end": 1533.63,
            "text": "heteron amplifier."
          },
          {
            "start": 1535.01,
            "end": 1535.71,
            "text": "Eigen"
          },
          {
            "start": 1535.71,
            "end": 1535.71,
            "text": ""
          },
          {
            "start": 1535.93,
            "end": 1536.07,
            "text": "Gerg,"
          },
          {
            "start": 1536.09,
            "end": 1536.15,
            "text": "filen,"
          },
          {
            "start": 1536.17,
            "end": 1537.13,
            "text": "marbelent"
          },
          {
            "start": 1537.13,
            "end": 1539.15,
            "text": "crisarnish"
          },
          {
            "start": 1539.15,
            "end": 1540.19,
            "text": "cái"
          },
          {
            "start": 1540.19,
            "end": 1542.35,
            "text": "limbaanen,"
          },
          {
            "start": 1542.35,
            "end": 1542.45,
            "text": "kar ghee,"
          },
          {
            "start": 1542.45,
            "end": 1547.99,
            "text": "En dan komik nahr hiz, dan ze lew el kander wir sprik."
          },
          {
            "start": 1549.69,
            "end": 1557.93,
            "text": "Duz dit is de laatste priftieki ischref, kijk sa vums margut in de krant."
          },
          {
            "start": 1559.43,
            "end": 1563.93,
            "text": "Dan metje prussis war ik pen en ik blef,"
          },
          {
            "start": 1564.65,
            "end": 1567.51,
            "text": "For da dik weertrich kom in klant."
          },
          {
            "start": 1570.1699999999998,
            "end": 1575.23,
            "text": "Siegte lich ischref, kijk sa vums margut in klant."
          },
          {
            "start": 1575.23,
            "end": 1579.29,
            "text": "Dan metje prussis, kijk sa vums margut in klant."
          },
          {
            "start": 1579.29,
            "end": 1582.95,
            "text": "Ich weertrich kom in klant."
          },
          {
            "start": 1583.95,
            "end": 1587.95,
            "text": "En datje an de kaiselt staan,"
          },
          {
            "start": 1589.17,
            "end": 1593.75,
            "text": "Siegte lich ischref, kijk sa vums margut in klant."
          },
          {
            "start": 1593.75,
            "end": 1598.05,
            "text": "Die soweken jogen kijk,"
          },
          {
            "start": 1599.47,
            "end": 1602.17,
            "text": "Die soweken jogen kijk, die soweken jogen kijk,"
          },
          {
            "start": 1602.17,
            "end": 1612.39,
            "text": "Die soweken jogen kijk, die soweken jogen kijk,"
          },
          {
            "start": 1612.39,
            "end": 1621.27,
            "text": "Na na na na na na na na na na na na na na na na"
          },
          {
            "start": 1621.27,
            "end": 1625.53,
            "text": "12. Schatt, dan ik veel van je hao"
          },
          {
            "start": 1625.53,
            "end": 1630.05,
            "text": "Dat hoef ik je niet te verklaren"
          },
          {
            "start": 1630.05,
            "end": 1635.09,
            "text": "En zeh man is toll op z'n kenderen en vrao"
          },
          {
            "start": 1635.09,
            "end": 1639.37,
            "text": "Maar toch wil ei alteid weer waren"
          },
          {
            "start": 1640.01,
            "end": 1642.57,
            "text": "Maar heeft somst du zeh"
          },
          {
            "start": 1642.57,
            "end": 1644.55,
            "text": "Its verkeerts met me vor"
          },
          {
            "start": 1644.55,
            "end": 1647.99,
            "text": "En kreig ik vor goetavere"
          },
          {
            "start": 1650.01,
            "end": 1654.27,
            "text": "Denk dan en ons kenderen en slajr dor"
          },
          {
            "start": 1654.27,
            "end": 1658.81,
            "text": "Maarts brek ga ar dan dik wil svan mei"
          },
          {
            "start": 1660.65,
            "end": 1665.13,
            "text": "Ziek te lich is van des gelde"
          },
          {
            "start": 1665.13,
            "end": 1669.49,
            "text": "Dann gaat m'n hart wat sneller slam"
          },
          {
            "start": 1670.0100000000002,
            "end": 1674.41,
            "text": "Ik weet dat jij op mij z'n't watten"
          },
          {
            "start": 1674.41,
            "end": 1678.79,
            "text": "En dat je aan de keizelstam"
          },
          {
            "start": 1678.79,
            "end": 1683.45,
            "text": "Ziek te lich is van des gelde"
          },
          {
            "start": 1683.45,
            "end": 1688.83,
            "text": "Isto wekin ja hoge keik"
          },
          {
            "start": 1688.83,
            "end": 1693.51,
            "text": "Die me heel wil lief's vertellen"
          },
          {
            "start": 1693.51,
            "end": 1698.63,
            "text": "Dan ben i chazen prins opren"
          },
          {
            "start": 1698.63,
            "end": 1703.39,
            "text": "Four мыz iset voe hij eina"
          },
          {
            "start": 1703.39,
            "end": 1713.67,
            "text": "Vàm vienenne n-u"
          },
          {
            "start": 1713.67,
            "end": 1714.41,
            "text": "Wat hoaf"
          },
          {
            "start": 1714.41,
            "end": 1716.63,
            "text": "La niersjped i s sslab"
          },
          {
            "start": 1716.63,
            "end": 1716.63,
            "text": ""
          },
          {
            "start": 1716.63,
            "end": 1716.63,
            "text": ""
          }
        ],
        "words": [],
        "confidence": 0.8,
        "engine": "whisper",
        "audio_file": "app\\data\\training\\d840b70f-bf01-4b84-84ef-5c6a4b663d4e\\audio_000.wav"
      }
    ],
    "rvc_model_trained": true,
    "rvc_model_path": "backend\\app\\data\\models\\ttt.pth"
  }
}